wangruilin.py
wangruilin-1.0.dist-info/METADATA
wangruilin-1.0.dist-info/WHEEL
wangruilin-1.0.dist-info/top_level.txt
wangruilin-1.0.dist-info/RECORD
