Metadata-Version: 2.1
Name: wangruilin
Version: 1.0
Summary: for say
Home-page: https://github.com/upuuuuuu
Author: upuuuuuu
Author-email: 2226548059@qq.com
License: MIT
